store/__init__.py
store/py.typed
babichjacob_store-0.5.0.dist-info/WHEEL
babichjacob_store-0.5.0.dist-info/METADATA
babichjacob_store-0.5.0.dist-info/RECORD
