Metadata-Version: 2.1
Name: babichjacob-store
Version: 0.5.0
Summary: A Python implementation of svelte/store
Home-page: https://github.com/babichjacob/python-store
License: MIT
Author: J or Jacob Babich
Author-email: jacobbabichpublic+git@gmail.com
Requires-Python: >=3.7,<4.0
Classifier: License :: OSI Approved :: MIT License
Classifier: Programming Language :: Python :: 3
Classifier: Programming Language :: Python :: 3.7
Classifier: Programming Language :: Python :: 3.8
Classifier: Programming Language :: Python :: 3.9
Classifier: Programming Language :: Python :: 3.10
Classifier: Programming Language :: Python :: 3.11
Project-URL: Repository, https://github.com/babichjacob/python-store
